[
  {
    "id": "javascript",
    "name": "JavaScript",
    "color": "#bb8a1b"
  },
  {
    "id": "typescript",
    "name": "TypeScript",
    "color": "#007ACC"
  },
  {
    "id": "nextjs",
    "name": "Next.js",
    "color": "#000000"
  },
  {
    "id": "react",
    "name": "React",
    "color": "#399fba"
  },
  {
    "id": "postgresql",
    "name": "PostgreSQL",
    "color": "#396691"
  },
  {
    "id": "githubactions",
    "name": "GitHub Actions",
    "color": "#278CFF"
  },
  {
    "id": "html",
    "name": "HTML",
    "color": "#E44D26"
  },
  {
    "id": "css",
    "name": "CSS",
    "color": "#2965F1"
  },
  {
    "id": "sass",
    "name": "Sass",
    "color": "#CC6699"
  },
  {
    "id": "tailwind",
    "name": "Tailwind",
    "color": "#38B2AC"
  },
  {
    "id": "vitest",
    "name": "Vitest",
    "color": "#769E22"
  },
  {
    "id": "reacttestinglibrary",
    "name": "React Testing Library",
    "color": "#CC2524"
  },
  {
    "id": "cypress",
    "name": "Cypress",
    "color": "#57C592"
  },
  {
    "id": "trpc",
    "name": "tRPC",
    "color": "#398CCB"
  },
  {
    "id": "vercel",
    "name": "Vercel",
    "color": "#000000"
  },
  {
    "id": "netlify",
    "name": "Netlify",
    "color": "#00C7B7"
  },
  {
    "id": "digitalocean",
    "name": "Digital Ocean",
    "color": "#0080FF"
  },
  {
    "id": "zod",
    "name": "Zod",
    "color": "#1B2D47"
  },
  {
    "id": "prisma",
    "name": "Prisma",
    "color": "#5A67D8"
  },
  {
    "id": "docker",
    "name": "Docker",
    "color": "#2496ED"
  },
  {
    "id": "vite",
    "name": "Vite",
    "color": "#646CFF"
  },
  {
    "id": "reactspring",
    "name": "React Spring",
    "color": "#88B04B"
  },
  {
    "id": "reactquery",
    "name": "React Query",
    "color": "#FF4154"
  },
  {
    "id": "authjs",
    "name": "AuthJS",
    "color": "#FB7208"
  },
  {
    "id": "api",
    "name": "API",
    "color": "#6BB56C"
  },
  {
    "id": "spline",
    "name": "Spline",
    "color": "#FE40F3"
  },
  {
    "id": "editorjs",
    "name": "Editor.js",
    "color": "#369FF7"
  },
  {
    "id": "electron",
    "name": "Electron",
    "color": "#47848F"
  },
  {
    "id": "bem",
    "name": "BEM",
    "color": "#1C89BF"
  },
  {
    "id": "themeui",
    "name": "Theme UI",
    "color": "#61DAFB"
  },
  {
    "id": "strapi",
    "name": "Strapi",
    "color": "#2E7EE5"
  },
  {
    "id": "resend",
    "name": "Resend",
    "color": "#FF9800"
  },
  {
    "id": "html2canvas",
    "name": "HTML2Canvas",
    "color": "#F46542"
  },
  {
    "id": "pwa",
    "name": "PWA",
    "color": "#0AC857"
  },
  {
    "id": "redux",
    "name": "Redux (RTK)",
    "color": "#764ABC"
  },
  {
    "id": "reactrouter",
    "name": "React Router",
    "color": "#D10A22"
  },
  {
    "id": "githubpages",
    "name": "GitHub Pages",
    "color": "#0B2F64"
  },
  {
    "id": "cicd",
    "name": "CI/CD",
    "color": "#F4AA3E"
  }
]